[{"place_id": 237023741, "licence": "Data \u00a9 OpenStreetMap contributors, ODbL 1.0. http://osm.org/copyright", "osm_type": "node", "osm_id": 7132880190, "lat": "23.0652856", "lon": "72.5960835", "class": "leisure", "type": "garden", "place_rank": 30, "importance": 6.633783474474735e-05, "addresstype": "leisure", "name": "Riverfront Children's Park", "display_name": "Riverfront Children's Park, Sabarmati Riverfront Promenade, Dudheshwar, Asarva Taluka, Ahmedabad, Gujarat, 380014, India", "boundingbox": ["23.0652356", "23.0653356", "72.5960335", "72.5961335"], "geojson": {"type": "Point", "coordinates": [72.5960835, 23.0652856]}}]